sftp/__init__.py
sftp/ftp.py
shttp/__init__.py
shttp/handler.py
simple_ftp-0.2.0.dist-info/AUTHORS
simple_ftp-0.2.0.dist-info/METADATA
simple_ftp-0.2.0.dist-info/WHEEL
simple_ftp-0.2.0.dist-info/pbr.json
simple_ftp-0.2.0.dist-info/top_level.txt
simple_ftp-0.2.0.dist-info/RECORD
